{"trial_id": "00", "hyperparameters": {"space": [{"class_name": "Int", "config": {"name": "num_dense_layers", "default": null, "conditions": [], "min_value": 5, "max_value": 20, "step": 3, "sampling": "linear"}}, {"class_name": "Int", "config": {"name": "num_neurons_first_hidden", "default": null, "conditions": [], "min_value": 50, "max_value": 500, "step": 50, "sampling": "linear"}}, {"class_name": "Float", "config": {"name": "dropout_rate", "default": 0.1, "conditions": [], "min_value": 0.1, "max_value": 0.4, "step": 0.1, "sampling": "linear"}}, {"class_name": "Float", "config": {"name": "learning_rate", "default": 1e-05, "conditions": [], "min_value": 1e-05, "max_value": 0.001, "step": null, "sampling": "log"}}, {"class_name": "Choice", "config": {"name": "activation", "default": "relu", "conditions": [], "values": ["relu", "leaky_relu", "softplus", "swish"], "ordered": false}}], "values": {"num_dense_layers": 20, "num_neurons_first_hidden": 100, "dropout_rate": 0.2, "learning_rate": 4.9547586024235816e-05, "activation": "leaky_relu"}}, "metrics": {"metrics": {"loss": {"direction": "min", "observations": [{"value": [0.3875645697116852], "step": 657}]}, "poisson": {"direction": "min", "observations": [{"value": [0.38756459951400757], "step": 657}]}, "root_mean_squared_error": {"direction": "min", "observations": [{"value": [0.37277141213417053], "step": 657}]}, "mean_absolute_error": {"direction": "min", "observations": [{"value": [0.23001061379909515], "step": 657}]}, "val_loss": {"direction": "min", "observations": [{"value": [0.3716125786304474], "step": 657}]}, "val_poisson": {"direction": "min", "observations": [{"value": [0.3716125786304474], "step": 657}]}, "val_root_mean_squared_error": {"direction": "min", "observations": [{"value": [0.36212462186813354], "step": 657}]}, "val_mean_absolute_error": {"direction": "min", "observations": [{"value": [0.2248789519071579], "step": 657}]}}}, "score": 0.3716125786304474, "best_step": 657, "status": "COMPLETED", "message": null}